autonoma/__init__.py
autonoma/main.py
autonoma/models/__init__.py
autonoma/models/agent.py
autonoma/models/code.py
autonoma/models/coder.py
autonoma/models/excecution.py
autonoma/models/project.py
autonoma/models/request.py
autonoma/models/result.py
autonoma/models/task.py
autonoma/models/test.py
autonoma-0.1.0.dist-info/METADATA
autonoma-0.1.0.dist-info/WHEEL
autonoma-0.1.0.dist-info/top_level.txt
autonoma-0.1.0.dist-info/RECORD
